{
    "response":{
        "shippingGroups":[
            {
                "taxPriceInfo":{
                    "cityTax":1.03,
                    "secondaryCurrencyTaxAmount":0,
                    "amount":7.9825,
                    "valueAddedTax":0,
                    "countyTax":0.2575,
                    "isTaxIncluded":false,
                    "miscTax":0,
                    "districtTax":0.515,
                    "stateTax":6.18,
                    "countryTax":0
                },
                "priceInfo":{
                    "discounted":false,
                    "amount":102.99,
                    "taxable":102.99,
                    "shippingSurchargeValue":5,
                    "manualAdjustmentTotal":0,
                    "discountAmount":0,
                    "tax":7.9825,
                    "rawSubtotal":102.99,
                    "subTotal":102.99,
                    "totalWithoutTax":122.94,
                    "total":130.9225,
                    "lkpValExcludingFreeShip":null,
                    "shipping":14.95,
                    "amountIsFinal":true,
                    "currencyCode":"USD"
                },
                "shippingMethod":{
                    "secondaryCurrencyTaxAmount":0,
                    "shippingTax":0,
                    "cost":5,
                    "taxable":5,
                    "taxIncluded": true,
                    "taxDetails":{
                        "jurisType":"state",
                        "rate":0.2,
                        "tax":1,
                        "taxName":"state tax"
                    },
                    "rate":0,
                    "tax":1,
                    "taxCode":"",
                    "value":"sm10001",
                    "shippingMethodDescription":"FlatRateShipping"
                },
                "shippingGroupId":"sg111691",
                "type":"hardgoodShippingGroup",
                "items":[
                    {
                        "rawTotalPrice":102.99,
                        "taxDetails":[
                            {
                                "jurisType":"Special",
                                "rate":0.005,
                                "tax":0.515,
                                "taxName":"CA SPECIAL TAX"
                            },
                            {
                                "jurisType":"Special",
                                "rate":0.01,
                                "tax":1.03,
                                "taxName":"CA SPECIAL TAX"
                            },
                            {
                                "jurisType":"County",
                                "rate":0.0025,
                                "tax":0.2575,
                                "taxName":"CA COUNTY TAX"
                            },
                            {
                                "jurisType":"State",
                                "rate":0.06,
                                "tax":6.18,
                                "taxName":"CA STATE TAX"
                            }
                        ],
                        "returnedQuantity":0,
                        "dynamicProperties":[],
                        "shippingSurchargeValue":5,
                        "discountAmount":0,
                        "externalData":[],
                        "preOrderQuantity":0,
                        "commerceItemId":"ci11000941",
                        "price":102.99,
                        "onSale":false,
                        "commerceId":"ci11000941",
                        "stateDetailsAsUser":"The item has been initialized within the shipping group",
                        "unitPrice":102.99,
                        "quantity":1,
                        "taxable":102.99,
                        "productId":"TallWindshield",
                        "salePrice":0,
                        "tax":7.9825,
                        "catRefId":"SMA8JP963000",
                        "discountInfo":[],
                        "shopperInput":{},
                        "backOrderQuantity":0,
                        "listPrice":102.99,
                        "status":"INITIAL"
                    }
                ]
            }
        ],
        "isTaxIncluded":false,
        "orderId":"o111691",
        "orderStatus":"Incomplete",
        "creationDate":"2023-01-27T00:44:43.511Z",
        "orderProfileId":8046636,
        "taxDate":"01-31-2023",
        "callType":"SalesOrder",
        "status":"success",
        "timestamp":"2023-01-27T00:45:08.011Z"
    }
}